odoo/addons/mrp_bom_priority/README.rst
odoo/addons/mrp_bom_priority/__init__.py
odoo/addons/mrp_bom_priority/__manifest__.py
odoo/addons/mrp_bom_priority/i18n/fr.po
odoo/addons/mrp_bom_priority/i18n/it.po
odoo/addons/mrp_bom_priority/i18n/mrp_bom_priority.pot
odoo/addons/mrp_bom_priority/models/__init__.py
odoo/addons/mrp_bom_priority/models/mrp_bom.py
odoo/addons/mrp_bom_priority/readme/CONTRIBUTORS.rst
odoo/addons/mrp_bom_priority/readme/DESCRIPTION.rst
odoo/addons/mrp_bom_priority/static/description/icon.png
odoo/addons/mrp_bom_priority/static/description/index.html
odoo/addons/mrp_bom_priority/static/description/mrp_bom_view_form.jpeg
odoo/addons/mrp_bom_priority/static/description/mrp_bom_view_tree.jpeg
odoo/addons/mrp_bom_priority/tests/__init__.py
odoo/addons/mrp_bom_priority/tests/test_mrp_bom_priority.py
odoo/addons/mrp_bom_priority/views/view_mrp_bom.xml
odoo_addon_mrp_bom_priority-16.0.1.0.0.6.dist-info/METADATA
odoo_addon_mrp_bom_priority-16.0.1.0.0.6.dist-info/WHEEL
odoo_addon_mrp_bom_priority-16.0.1.0.0.6.dist-info/top_level.txt
odoo_addon_mrp_bom_priority-16.0.1.0.0.6.dist-info/RECORD
